polarscnj-1.0.2.dist-info/METADATA
polarscnj-1.0.2.dist-info/WHEEL
polarscnj-1.0.2.dist-info/license_files/LICENSE
polars/datatypes.py
polars/exceptions.py
polars/io.py
polars/datatypes_constructor.py
polars/show_versions.py
polars/build_info.py
polars/cfg.py
polars/internals/functions.py
polars/internals/io.py
polars/internals/whenthen.py
polars/internals/dataframe/groupby.py
polars/internals/dataframe/pivot.py
polars/internals/dataframe/__init__.py
polars/internals/dataframe/frame.py
polars/internals/lazyframe/groupby.py
polars/internals/lazyframe/__init__.py
polars/internals/lazyframe/frame.py
polars/internals/construction.py
polars/internals/type_aliases.py
polars/internals/lazy_functions.py
polars/internals/slice.py
polars/internals/expr/string.py
polars/internals/expr/struct.py
polars/internals/expr/expr.py
polars/internals/expr/list.py
polars/internals/expr/meta.py
polars/internals/expr/__init__.py
polars/internals/expr/datetime.py
polars/internals/expr/categorical.py
polars/internals/series/string.py
polars/internals/series/struct.py
polars/internals/series/list.py
polars/internals/series/series.py
polars/internals/series/_numpy.py
polars/internals/series/__init__.py
polars/internals/series/utils.py
polars/internals/series/datetime.py
polars/internals/series/categorical.py
polars/internals/__init__.py
polars/internals/anonymous_scan.py
polars/internals/sql/context.py
polars/internals/sql/__init__.py
polars/internals/batched.py
polars/convert.py
polars/dependencies.py
polars/string_cache.py
polars/_html.py
polars/__init__.py
polars/testing/asserts.py
polars/testing/parametric.py
polars/testing/_private.py
polars/testing/_parametric.py
polars/testing/__init__.py
polars/utils.py
polars/py.typed
polars/api.py
polars/polars.cpython-38-x86_64-linux-gnu.so
polarscnj-1.0.2.dist-info/RECORD
