Metadata-Version: 2.1
Name: polarscnj
Version: 1.0.2
Requires-Dist: typing_extensions >= 4.0.0; python_version < '3.10'
Requires-Dist: pyarrow>=4.0.0; extra == 'pandas'
Requires-Dist: pandas; extra == 'pandas'
Requires-Dist: polars[pyarrow,pandas,numpy,fsspec,connectorx,xlsx2csv,timezone,matplotlib]; extra == 'all'
Requires-Dist: numpy >= 1.16.0; extra == 'numpy'
Requires-Dist: xlsx2csv >= 0.8.0; extra == 'xlsx2csv'
Requires-Dist: backports.zoneinfo; (python_version < '3.9') and extra == 'timezone'
Requires-Dist: tzdata; (platform_system == 'Windows') and extra == 'timezone'
Requires-Dist: connectorx; extra == 'connectorx'
Requires-Dist: matplotlib; extra == 'matplotlib'
Requires-Dist: fsspec; extra == 'fsspec'
Requires-Dist: pyarrow>=4.0.0; extra == 'pyarrow'
Provides-Extra: pandas
Provides-Extra: all
Provides-Extra: numpy
Provides-Extra: xlsx2csv
Provides-Extra: timezone
Provides-Extra: connectorx
Provides-Extra: matplotlib
Provides-Extra: fsspec
Provides-Extra: pyarrow
License-File: LICENSE
Summary: Fork from polars repository, faster conversions to python. All of this was made possible by the incredible work of ritchie46.
Home-Page: https://github.com/koga25/polars-private
Author: koga25 <lucasvas100@gmail.com>
Author-email: koga25 <lucasvas100@gmail.com>
License: MIT
Requires-Python: >=3.7
Project-URL: Source Code, https://github.com/koga25/polars-private
